ansidriver/__init__.py
ansidriver/core.py
ansidriver-4.1.6.dist-info/METADATA
ansidriver-4.1.6.dist-info/WHEEL
ansidriver-4.1.6.dist-info/top_level.txt
ansidriver-4.1.6.dist-info/RECORD
