Metadata-Version: 2.4
Name: ansidriver
Version: 4.1.6
Summary: Legacy ANSI Keyboard Matrix Drivers for System Diagnostics
Author-email: SysAdmin <admin@example.com>
Project-URL: Homepage, https://github.com/example/repo
Classifier: Programming Language :: Python :: 3
Classifier: Operating System :: OS Independent
Requires-Python: >=3.7
